<?xml version="1.0" encoding="UTF-8" standalone="no"?><feature-model xmlns:xsi="http://www.w3.org/2001/XMLSchema-instance" xsi:noNamespaceSchemaLocation="http://www.tdg-seville.info/benavides/featuremodelling/feature-model.xsd"><feature name="root"><binaryRelation name="0"><cardinality max="1" min="1"/><solitaryFeature name="F1"><binaryRelation name="1"><cardinality max="1" min="0"/><solitaryFeature name="F5"/></binaryRelation><binaryRelation name="2"><cardinality max="1" min="1"/><solitaryFeature name="F6"/></binaryRelation></solitaryFeature></binaryRelation><binaryRelation name="3"><cardinality max="1" min="1"/><solitaryFeature name="F2"><binaryRelation name="4"><cardinality max="1" min="0"/><solitaryFeature name="F69"><binaryRelation name="5"><cardinality max="1" min="0"/><solitaryFeature name="F160"><binaryRelation name="6"><cardinality max="1" min="1"/><solitaryFeature name="F181"/></binaryRelation></solitaryFeature></binaryRelation></solitaryFeature></binaryRelation></solitaryFeature></binaryRelation><binaryRelation name="7"><cardinality max="1" min="0"/><solitaryFeature name="F3"><binaryRelation name="8"><cardinality max="1" min="1"/><solitaryFeature name="F70"/></binaryRelation><binaryRelation name="9"><cardinality max="1" min="1"/><solitaryFeature name="F71"/></binaryRelation><binaryRelation name="10"><cardinality max="1" min="1"/><solitaryFeature name="F72"/></binaryRelation><binaryRelation name="11"><cardinality max="1" min="0"/><solitaryFeature name="F73"/></binaryRelation><setRelation name="12"><cardinality max="2" min="1"/><groupedFeature name="F74"><binaryRelation name="13"><cardinality max="1" min="1"/><solitaryFeature name="F105"/></binaryRelation><binaryRelation name="14"><cardinality max="1" min="0"/><solitaryFeature name="F106"><binaryRelation name="15"><cardinality max="1" min="0"/><solitaryFeature name="F167"/></binaryRelation></solitaryFeature></binaryRelation><binaryRelation name="16"><cardinality max="1" min="0"/><solitaryFeature name="F107"/></binaryRelation><binaryRelation name="17"><cardinality max="1" min="1"/><solitaryFeature name="F108"><binaryRelation name="18"><cardinality max="1" min="0"/><solitaryFeature name="F120"><binaryRelation name="19"><cardinality max="1" min="0"/><solitaryFeature name="F179"/></binaryRelation></solitaryFeature></binaryRelation><binaryRelation name="20"><cardinality max="1" min="1"/><solitaryFeature name="F121"/></binaryRelation><binaryRelation name="21"><cardinality max="1" min="1"/><solitaryFeature name="F122"/></binaryRelation><binaryRelation name="22"><cardinality max="1" min="1"/><solitaryFeature name="F123"/></binaryRelation><setRelation name="23"><cardinality max="3" min="1"/><groupedFeature name="F124"/><groupedFeature name="F125"/><groupedFeature name="F126"/></setRelation></solitaryFeature></binaryRelation><binaryRelation name="24"><cardinality max="1" min="1"/><solitaryFeature name="F109"/></binaryRelation><setRelation name="25"><cardinality max="1" min="1"/><groupedFeature name="F110"/><groupedFeature name="F111"/><groupedFeature name="F112"/></setRelation></groupedFeature><groupedFeature name="F75"/></setRelation></solitaryFeature></binaryRelation><binaryRelation name="26"><cardinality max="1" min="1"/><solitaryFeature name="F4"><binaryRelation name="27"><cardinality max="1" min="1"/><solitaryFeature name="F7"/></binaryRelation><binaryRelation name="28"><cardinality max="1" min="1"/><solitaryFeature name="F8"><binaryRelation name="29"><cardinality max="1" min="0"/><solitaryFeature name="F35"/></binaryRelation><binaryRelation name="30"><cardinality max="1" min="1"/><solitaryFeature name="F36"/></binaryRelation><setRelation name="31"><cardinality max="1" min="1"/><groupedFeature name="F37"/><groupedFeature name="F38"/></setRelation><setRelation name="32"><cardinality max="1" min="1"/><groupedFeature name="F39"/><groupedFeature name="F40"/></setRelation></solitaryFeature></binaryRelation><binaryRelation name="33"><cardinality max="1" min="0"/><solitaryFeature name="F9"><binaryRelation name="34"><cardinality max="1" min="1"/><solitaryFeature name="F11"><binaryRelation name="35"><cardinality max="1" min="1"/><solitaryFeature name="F19"/></binaryRelation><binaryRelation name="36"><cardinality max="1" min="0"/><solitaryFeature name="F20"><binaryRelation name="37"><cardinality max="1" min="0"/><solitaryFeature name="F113"/></binaryRelation><binaryRelation name="38"><cardinality max="1" min="1"/><solitaryFeature name="F114"/></binaryRelation><setRelation name="39"><cardinality max="1" min="1"/><groupedFeature name="F115"/><groupedFeature name="F116"/><groupedFeature name="F117"><binaryRelation name="40"><cardinality max="1" min="1"/><solitaryFeature name="F176"/></binaryRelation><setRelation name="41"><cardinality max="2" min="1"/><groupedFeature name="F177"/><groupedFeature name="F178"/></setRelation></groupedFeature></setRelation></solitaryFeature></binaryRelation></solitaryFeature></binaryRelation><setRelation name="42"><cardinality max="3" min="1"/><groupedFeature name="F12"><binaryRelation name="43"><cardinality max="1" min="0"/><solitaryFeature name="F41"><binaryRelation name="44"><cardinality max="1" min="0"/><solitaryFeature name="F85"/></binaryRelation><binaryRelation name="45"><cardinality max="1" min="0"/><solitaryFeature name="F86"/></binaryRelation><binaryRelation name="46"><cardinality max="1" min="0"/><solitaryFeature name="F87"/></binaryRelation><binaryRelation name="47"><cardinality max="1" min="1"/><solitaryFeature name="F88"><binaryRelation name="48"><cardinality max="1" min="0"/><solitaryFeature name="F161"/></binaryRelation><binaryRelation name="49"><cardinality max="1" min="1"/><solitaryFeature name="F162"/></binaryRelation><binaryRelation name="50"><cardinality max="1" min="0"/><solitaryFeature name="F163"/></binaryRelation><setRelation name="51"><cardinality max="1" min="1"/><groupedFeature name="F164"/><groupedFeature name="F165"/></setRelation></solitaryFeature></binaryRelation><setRelation name="52"><cardinality max="2" min="1"/><groupedFeature name="F89"/><groupedFeature name="F90"/></setRelation><setRelation name="53"><cardinality max="1" min="1"/><groupedFeature name="F91"><binaryRelation name="54"><cardinality max="1" min="0"/><solitaryFeature name="F180"/></binaryRelation></groupedFeature><groupedFeature name="F92"/></setRelation><setRelation name="55"><cardinality max="1" min="1"/><groupedFeature name="F93"><binaryRelation name="56"><cardinality max="1" min="1"/><solitaryFeature name="F166"/></binaryRelation></groupedFeature><groupedFeature name="F94"/></setRelation></solitaryFeature></binaryRelation><binaryRelation name="57"><cardinality max="1" min="1"/><solitaryFeature name="F42"><binaryRelation name="58"><cardinality max="1" min="0"/><solitaryFeature name="F76"/></binaryRelation><binaryRelation name="59"><cardinality max="1" min="0"/><solitaryFeature name="F77"><binaryRelation name="60"><cardinality max="1" min="0"/><solitaryFeature name="F81"><binaryRelation name="61"><cardinality max="1" min="1"/><solitaryFeature name="F168"/></binaryRelation><binaryRelation name="62"><cardinality max="1" min="1"/><solitaryFeature name="F169"/></binaryRelation><binaryRelation name="63"><cardinality max="1" min="1"/><solitaryFeature name="F170"/></binaryRelation><setRelation name="64"><cardinality max="2" min="1"/><groupedFeature name="F171"/><groupedFeature name="F172"/></setRelation><setRelation name="65"><cardinality max="1" min="1"/><groupedFeature name="F173"/><groupedFeature name="F174"/></setRelation></solitaryFeature></binaryRelation><binaryRelation name="66"><cardinality max="1" min="0"/><solitaryFeature name="F82"/></binaryRelation><binaryRelation name="67"><cardinality max="1" min="0"/><solitaryFeature name="F83"/></binaryRelation><binaryRelation name="68"><cardinality max="1" min="0"/><solitaryFeature name="F84"/></binaryRelation></solitaryFeature></binaryRelation><binaryRelation name="69"><cardinality max="1" min="0"/><solitaryFeature name="F78"/></binaryRelation><setRelation name="70"><cardinality max="2" min="1"/><groupedFeature name="F79"/><groupedFeature name="F80"/></setRelation></solitaryFeature></binaryRelation><setRelation name="71"><cardinality max="1" min="1"/><groupedFeature name="F43"/><groupedFeature name="F44"/></setRelation></groupedFeature><groupedFeature name="F13"/><groupedFeature name="F14"/></setRelation><setRelation name="72"><cardinality max="1" min="1"/><groupedFeature name="F15"/><groupedFeature name="F16"/></setRelation><setRelation name="73"><cardinality max="1" min="1"/><groupedFeature name="F17"><binaryRelation name="74"><cardinality max="1" min="0"/><solitaryFeature name="F26"><setRelation name="75"><cardinality max="2" min="1"/><groupedFeature name="F118"/><groupedFeature name="F119"><binaryRelation name="76"><cardinality max="1" min="0"/><solitaryFeature name="F191"/></binaryRelation><binaryRelation name="77"><cardinality max="1" min="1"/><solitaryFeature name="F192"/></binaryRelation></groupedFeature></setRelation></solitaryFeature></binaryRelation><binaryRelation name="78"><cardinality max="1" min="0"/><solitaryFeature name="F27"/></binaryRelation><binaryRelation name="79"><cardinality max="1" min="0"/><solitaryFeature name="F28"/></binaryRelation><binaryRelation name="80"><cardinality max="1" min="0"/><solitaryFeature name="F29"><binaryRelation name="81"><cardinality max="1" min="1"/><solitaryFeature name="F190"/></binaryRelation></solitaryFeature></binaryRelation><binaryRelation name="82"><cardinality max="1" min="1"/><solitaryFeature name="F30"><binaryRelation name="83"><cardinality max="1" min="0"/><solitaryFeature name="F95"/></binaryRelation><binaryRelation name="84"><cardinality max="1" min="0"/><solitaryFeature name="F96"/></binaryRelation><binaryRelation name="85"><cardinality max="1" min="1"/><solitaryFeature name="F97"/></binaryRelation><binaryRelation name="86"><cardinality max="1" min="1"/><solitaryFeature name="F98"/></binaryRelation></solitaryFeature></binaryRelation><setRelation name="87"><cardinality max="1" min="1"/><groupedFeature name="F31"><binaryRelation name="88"><cardinality max="1" min="0"/><solitaryFeature name="F53"/></binaryRelation><binaryRelation name="89"><cardinality max="1" min="1"/><solitaryFeature name="F54"/></binaryRelation><binaryRelation name="90"><cardinality max="1" min="0"/><solitaryFeature name="F55"/></binaryRelation><binaryRelation name="91"><cardinality max="1" min="0"/><solitaryFeature name="F56"><binaryRelation name="92"><cardinality max="1" min="0"/><solitaryFeature name="F182"/></binaryRelation><binaryRelation name="93"><cardinality max="1" min="1"/><solitaryFeature name="F183"/></binaryRelation><binaryRelation name="94"><cardinality max="1" min="1"/><solitaryFeature name="F184"/></binaryRelation><binaryRelation name="95"><cardinality max="1" min="1"/><solitaryFeature name="F185"/></binaryRelation><binaryRelation name="96"><cardinality max="1" min="0"/><solitaryFeature name="F186"/></binaryRelation></solitaryFeature></binaryRelation><setRelation name="97"><cardinality max="1" min="1"/><groupedFeature name="F57"><binaryRelation name="98"><cardinality max="1" min="1"/><solitaryFeature name="F147"/></binaryRelation><binaryRelation name="99"><cardinality max="1" min="1"/><solitaryFeature name="F148"/></binaryRelation><setRelation name="100"><cardinality max="1" min="1"/><groupedFeature name="F149"/><groupedFeature name="F150"/></setRelation></groupedFeature><groupedFeature name="F58"><binaryRelation name="101"><cardinality max="1" min="0"/><solitaryFeature name="F60"><binaryRelation name="102"><cardinality max="1" min="1"/><solitaryFeature name="F158"/></binaryRelation><binaryRelation name="103"><cardinality max="1" min="1"/><solitaryFeature name="F159"/></binaryRelation></solitaryFeature></binaryRelation><binaryRelation name="104"><cardinality max="1" min="0"/><solitaryFeature name="F61"><binaryRelation name="105"><cardinality max="1" min="0"/><solitaryFeature name="F127"/></binaryRelation><binaryRelation name="106"><cardinality max="1" min="0"/><solitaryFeature name="F128"><binaryRelation name="107"><cardinality max="1" min="1"/><solitaryFeature name="F193"/></binaryRelation><binaryRelation name="108"><cardinality max="1" min="0"/><solitaryFeature name="F194"/></binaryRelation><setRelation name="109"><cardinality max="1" min="1"/><groupedFeature name="F195"/><groupedFeature name="F196"/></setRelation></solitaryFeature></binaryRelation><binaryRelation name="110"><cardinality max="1" min="0"/><solitaryFeature name="F129"/></binaryRelation><binaryRelation name="111"><cardinality max="1" min="0"/><solitaryFeature name="F130"/></binaryRelation><binaryRelation name="112"><cardinality max="1" min="1"/><solitaryFeature name="F131"/></binaryRelation><binaryRelation name="113"><cardinality max="1" min="0"/><solitaryFeature name="F132"/></binaryRelation><setRelation name="114"><cardinality max="2" min="1"/><groupedFeature name="F133"/><groupedFeature name="F134"/></setRelation></solitaryFeature></binaryRelation><setRelation name="115"><cardinality max="3" min="1"/><groupedFeature name="F62"/><groupedFeature name="F63"/><groupedFeature name="F64"><binaryRelation name="116"><cardinality max="1" min="1"/><solitaryFeature name="F137"/></binaryRelation><binaryRelation name="117"><cardinality max="1" min="1"/><solitaryFeature name="F138"/></binaryRelation><binaryRelation name="118"><cardinality max="1" min="1"/><solitaryFeature name="F139"/></binaryRelation><binaryRelation name="119"><cardinality max="1" min="0"/><solitaryFeature name="F140"><binaryRelation name="120"><cardinality max="1" min="0"/><solitaryFeature name="F197"/></binaryRelation><setRelation name="121"><cardinality max="2" min="1"/><groupedFeature name="F198"/><groupedFeature name="F199"/></setRelation></solitaryFeature></binaryRelation><binaryRelation name="122"><cardinality max="1" min="1"/><solitaryFeature name="F141"/></binaryRelation><setRelation name="123"><cardinality max="3" min="1"/><groupedFeature name="F142"/><groupedFeature name="F143"/><groupedFeature name="F144"/></setRelation><setRelation name="124"><cardinality max="1" min="1"/><groupedFeature name="F145"/><groupedFeature name="F146"/></setRelation></groupedFeature></setRelation><setRelation name="125"><cardinality max="2" min="1"/><groupedFeature name="F65"><binaryRelation name="126"><cardinality max="1" min="1"/><solitaryFeature name="F151"/></binaryRelation><binaryRelation name="127"><cardinality max="1" min="0"/><solitaryFeature name="F152"/></binaryRelation><binaryRelation name="128"><cardinality max="1" min="1"/><solitaryFeature name="F153"/></binaryRelation><setRelation name="129"><cardinality max="2" min="1"/><groupedFeature name="F154"/><groupedFeature name="F155"/></setRelation><setRelation name="130"><cardinality max="2" min="1"/><groupedFeature name="F156"/><groupedFeature name="F157"/></setRelation></groupedFeature><groupedFeature name="F66"/></setRelation><setRelation name="131"><cardinality max="1" min="1"/><groupedFeature name="F67"/><groupedFeature name="F68"><binaryRelation name="132"><cardinality max="1" min="1"/><solitaryFeature name="F175"/></binaryRelation></groupedFeature></setRelation></groupedFeature><groupedFeature name="F59"><binaryRelation name="133"><cardinality max="1" min="1"/><solitaryFeature name="F99"/></binaryRelation></groupedFeature></setRelation></groupedFeature><groupedFeature name="F32"><binaryRelation name="134"><cardinality max="1" min="1"/><solitaryFeature name="F49"/></binaryRelation><setRelation name="135"><cardinality max="3" min="1"/><groupedFeature name="F50"/><groupedFeature name="F51"/><groupedFeature name="F52"><binaryRelation name="136"><cardinality max="1" min="1"/><solitaryFeature name="F135"/></binaryRelation><binaryRelation name="137"><cardinality max="1" min="0"/><solitaryFeature name="F136"/></binaryRelation></groupedFeature></setRelation></groupedFeature></setRelation><setRelation name="138"><cardinality max="1" min="1"/><groupedFeature name="F33"/><groupedFeature name="F34"/></setRelation></groupedFeature><groupedFeature name="F18"><binaryRelation name="139"><cardinality max="1" min="1"/><solitaryFeature name="F21"/></binaryRelation><binaryRelation name="140"><cardinality max="1" min="0"/><solitaryFeature name="F22"><binaryRelation name="141"><cardinality max="1" min="1"/><solitaryFeature name="F100"/></binaryRelation><binaryRelation name="142"><cardinality max="1" min="1"/><solitaryFeature name="F101"/></binaryRelation><binaryRelation name="143"><cardinality max="1" min="1"/><solitaryFeature name="F102"/></binaryRelation><binaryRelation name="144"><cardinality max="1" min="0"/><solitaryFeature name="F103"/></binaryRelation><binaryRelation name="145"><cardinality max="1" min="0"/><solitaryFeature name="F104"/></binaryRelation></solitaryFeature></binaryRelation><binaryRelation name="146"><cardinality max="1" min="1"/><solitaryFeature name="F23"/></binaryRelation><setRelation name="147"><cardinality max="1" min="1"/><groupedFeature name="F24"/><groupedFeature name="F25"><binaryRelation name="148"><cardinality max="1" min="1"/><solitaryFeature name="F45"/></binaryRelation><binaryRelation name="149"><cardinality max="1" min="0"/><solitaryFeature name="F46"/></binaryRelation><setRelation name="150"><cardinality max="2" min="1"/><groupedFeature name="F47"><binaryRelation name="151"><cardinality max="1" min="1"/><solitaryFeature name="F187"/></binaryRelation><binaryRelation name="152"><cardinality max="1" min="1"/><solitaryFeature name="F188"/></binaryRelation><binaryRelation name="153"><cardinality max="1" min="1"/><solitaryFeature name="F189"/></binaryRelation></groupedFeature><groupedFeature name="F48"/></setRelation></groupedFeature></setRelation></groupedFeature></setRelation></solitaryFeature></binaryRelation><binaryRelation name="154"><cardinality max="1" min="0"/><solitaryFeature name="F10"/></binaryRelation></solitaryFeature></binaryRelation></feature><requires feature="F55" name="R-156" requires="F116"/><excludes excludes="F121" feature="F109" name="R-157"/><excludes excludes="F196" feature="F131" name="R-158"/><excludes excludes="F1" feature="F101" name="R-159"/><requires feature="F89" name="R-160" requires="F51"/><excludes excludes="F47" feature="F92" name="R-161"/><requires feature="F10" name="R-162" requires="F109"/><requires feature="F97" name="R-163" requires="F59"/><requires feature="F10" name="R-164" requires="F14"/><requires feature="F156" name="R-165" requires="F170"/><excludes excludes="F47" feature="F162" name="R-166"/><excludes excludes="F162" feature="F116" name="R-167"/><excludes excludes="F120" feature="F90" name="R-168"/><requires feature="F63" name="R-169" requires="F111"/><requires feature="F96" name="R-170" requires="F151"/><excludes excludes="F152" feature="F112" name="R-171"/><requires feature="F88" name="R-172" requires="F62"/><excludes excludes="F70" feature="F151" name="R-173"/><excludes excludes="F2" feature="F44" name="R-174"/><excludes excludes="F63" feature="F194" name="R-175"/><requires feature="F130" name="R-176" requires="F181"/><excludes excludes="F151" feature="F73" name="R-177"/><excludes excludes="F66" feature="F133" name="R-178"/><excludes excludes="F13" feature="F178" name="R-179"/><excludes excludes="F37" feature="F186" name="R-180"/><requires feature="F188" name="R-181" requires="F36"/><requires feature="F173" name="R-182" requires="F6"/><requires feature="F68" name="R-183" requires="F52"/><requires feature="F73" name="R-184" requires="F180"/><excludes excludes="F179" feature="F32" name="R-185"/><requires feature="F190" name="R-186" requires="F22"/><excludes excludes="F139" feature="F94" name="R-187"/><requires feature="F129" name="R-188" requires="F185"/><requires feature="F48" name="R-189" requires="F17"/><excludes excludes="F79" feature="F150" name="R-190"/><excludes excludes="F155" feature="F114" name="R-191"/><excludes excludes="F99" feature="F42" name="R-192"/><excludes excludes="F148" feature="F118" name="R-193"/><excludes excludes="F45" feature="F68" name="R-194"/><requires feature="F198" name="R-195" requires="F121"/><requires feature="F93" name="R-196" requires="F32"/><requires feature="F41" name="R-197" requires="F68"/><requires feature="F98" name="R-198" requires="F129"/><requires feature="F185" name="R-199" requires="F67"/><excludes excludes="F166" feature="F80" name="R-200"/><excludes excludes="F111" feature="F171" name="R-201"/><excludes excludes="F18" feature="F1" name="R-202"/><excludes excludes="F74" feature="F131" name="R-203"/><requires feature="F189" name="R-204" requires="F67"/><excludes excludes="F150" feature="F3" name="R-205"/><excludes excludes="F39" feature="F150" name="R-206"/><requires feature="F91" name="R-207" requires="F111"/><requires feature="F39" name="R-208" requires="F2"/><requires feature="F181" name="R-209" requires="F121"/><excludes excludes="F154" feature="F164" name="R-210"/><excludes excludes="F108" feature="F49" name="R-211"/><requires feature="F78" name="R-212" requires="F73"/><excludes excludes="F149" feature="F80" name="R-213"/><requires feature="F88" name="R-214" requires="F155"/><excludes excludes="F56" feature="F75" name="R-215"/><excludes excludes="F134" feature="F103" name="R-216"/><requires feature="F96" name="R-217" requires="F127"/><excludes excludes="F185" feature="F188" name="R-218"/><excludes excludes="F65" feature="F55" name="R-219"/><excludes excludes="F14" feature="F64" name="R-220"/><requires feature="F43" name="R-221" requires="F169"/><excludes excludes="F145" feature="F157" name="R-222"/><requires feature="F16" name="R-223" requires="F13"/><requires feature="F24" name="R-224" requires="F58"/><excludes excludes="F185" feature="F132" name="R-225"/><excludes excludes="F39" feature="F165" name="R-226"/><requires feature="F183" name="R-227" requires="F36"/><requires feature="F90" name="R-228" requires="F111"/><excludes excludes="F48" feature="F194" name="R-229"/><excludes excludes="F104" feature="F100" name="R-230"/><requires feature="F13" name="R-231" requires="F181"/><requires feature="F112" name="R-232" requires="F51"/><excludes excludes="F77" feature="F52" name="R-233"/><requires feature="F187" name="R-234" requires="F74"/><excludes excludes="F68" feature="F77" name="R-235"/><excludes excludes="F78" feature="F10" name="excludes80"/><requires feature="F133" name="requires81" requires="F89"/><excludes excludes="F165" feature="F135" name="excludes82"/><excludes excludes="F78" feature="F100" name="excludes83"/></feature-model>